{
  "Enabled": false,
  "EnabledModules": {
    "unfairsRevengeCruel": null,
    "needlesslyComplicatedButton": null,
    "simonShorts": null,
    "rgbMaze": null,
    "greenArrowsModule": null,
    "15MysticLights": null,
    "simonStumbles": null,
    "fizzBuzzModule": null,
    "KudosudokuModule": null,
    "StareModule": null,
    "whiteout": null,
    "tenpins": null,
    "blindArrows": null,
    "mastermindRestricted": null,
    "gendercipher": null,
    "starstruck": null,
    "GSSurroundingButtons": null,
    "SimonV2": null,
    "VaricoloredSquaresModule": null,
    "colouredArrowsModule": null,
    "simonsUltimateShowdownModule": null,
    "cartinese": null,
    "NextInLine": null,
    "devilishEggs": null,
    "NotBitmapsModule": null,
    "threeLEDsModule": null,
    "ForgetTheColors": null,
    "HexamazeModule": null,
    "brushStrokes": null,
    "simonForgets": null,
    "unorderedKeys": null,
    "tashaSqueals": null,
    "orderedKeys": null,
    "Faulty14SegmentDisplayModule": null,
    "hexiomModule": null,
    "MoreCode": null,
    "chineseCounting": null,
    "disorderedKeys": null,
    "misorderedKeys": null,
    "GridlockModule": null,
    "TenButtonColorCode": null,
    "BigCircle": null,
    "theSpeaker": null,
    "ColorBrailleModule": null,
    "baccarat": null,
    "SimonShiftsModule": null,
    "timeKeeper": null,
    "ForgetAnyColor": null,
    "neutralization": null,
    "nonbinaryPuzzle": null,
    "alphabetButtons": null,
    "DiscoloredSquaresModule": null,
    "64": null,
    "notTheBulb": null,
    "triangle": null,
    "kataWireOrdering": null,
    "simonsStatement": null,
    "DecoloredSquaresModule": null,
    "BooleanNetwork": null,
    "theTriangleButton": null,
    "WorldsLargestButton": null,
    "thinkingWiresModule": null,
    "CornersModule": null,
    "footnotes": null,
    "colorHexagons": null,
    "RubiksCubeModule": null,
    "Color Decoding": null,
    "logicalButtonsModule": null,
    "JuxtacoloredSquaresModule": null,
    "NotWireSequence": null,
    "TheBulbModule": null,
    "WalkingCubeModule": null,
    "michaelsoftBinbows": null,
    "morseButtons": null,
    "symbolicTasha": null,
    "theGreenWireModule": null,
    "colorGrid": null,
    "MusicRhythms": null,
    "crystalMaze": null,
    "equations": null,
    "7": null,
    "handTurkey": null,
    "14": null,
    "NotColoredSquaresModule": null,
    "asciiMaze": null,
    "HexiEvilFMN": null,
    "LightBulbs": null,
    "NotWiresword": null,
    "borderedKeys": null,
    "colors_maximization": null,
    "WhiteArrows": null,
    "GSCorridors": null,
    "linkedWordleModule": null,
    "simonSelectsModule": null,
    "recordedKeys": null,
    "NotColoredSwitchesModule": null,
    "CyanArrows": null,
    "colormath": null,
    "scavengerHunt": null,
    "punctuationMarks": null,
    "notPlungerButtonModule": null,
    "R4YMultiColoredSwitches": null,
    "unpleasantSquares": null,
    "simonSenses": null,
    "flowerPatch": null,
    "GSXenocryst": null,
    "zendo": null,
    "RedHerring": null,
    "blindCircle": null,
    "simonScrambles": null,
    "fractalMaze": null,
    "codenames": null,
    "breakfastEgg": null,
    "mastermindRestrictedCruel": null,
    "deceptiveRainbowArrowsModule": null,
    "colorNumbers": null,
    "horribleMemory": null,
    "halliGalli": null,
    "hertz": null,
    "screw": null,
    "robitProgramming": null,
    "enaCipher": null,
    "digitalGrid": null,
    "ColoredSwitchesModule": null,
    "yellowArrowsModule": null,
    "maze3": null,
    "FollowTheLeaderModule": null,
    "NotKeypad": null,
    "xtrpasscodes": null,
    "SimonShapesModule": null,
    "ColoredSquaresModule": null,
    "SimonScreamsModule": null,
    "yoshiEgg": null,
    "watchingPaintDry": null,
    "smallCircle": null,
    "charms": null,
    "GSSimonShuffles": null,
    "doubleScreenModule": null,
    "algorithmia": null,
    "plagiarism": null,
    "buttonGrid": null,
    "SimonSendsModule": null,
    "ShapesBombs": null,
    "redArrowsModule": null,
    "faceOff": null,
    "ladders": null,
    "TheExplodingPen": null,
    "simonSaidModule": null,
    "midCircle": null,
    "GSPentabutton": null,
    "numpath": null,
    "colorOneTwo": null,
    "R4YUncoloredSwitches": null,
    "NotButton": null,
    "tallorderedKeys": null,
    "LightCycleModule": null,
    "mineseeker": null,
    "boozlesnap": null,
    "simonSupports": null,
    "stoichiometryModule": null,
    "faultyrgbMaze": null,
    "antistress": null,
    "spangledStars": null,
    "MandNs": null,
    "purpleArrowsModule": null,
    "luckyDice": null,
    "SilencedSimon": null,
    "webDesign": null,
    "blueArrowsModule": null,
    "NumberPad": null,
    "ReversedBooleanNetwork": null,
    "orangeArrowsModule": null,
    "leds": null,
    "candyLand": null,
    "GSDirectingButtons": null,
    "gyromaze": null,
    "impostor": null,
    "tealArrowsModule": null,
    "directionalButton": null,
    "ASquareModule": null,
    "ColorfulMadness": null,
    "simonSmothers": null,
    "inselectables": null,
    "UncoloredSquaresModule": null,
    "faultyChineseCounting": null,
    "MorseAMaze": null,
    "semamorse": null,
    "WonderCipher": null,
    "MinesweeperModule": null,
    "Updog": null,
    "shiftedMaze": null,
    "simonsSwarmModule": null,
    "GSMazeseeker": null,
    "melodyMemory": null,
    "SimonShoutsModule": null,
    "reorderedKeys": null,
    "OddOneOutModule": null,
    "MarbleTumbleModule": null,
    "kugelblitz": null,
    "calendar": null,
    "theSamsung": null,
    "NotPerspectivePegsModule": null,
    "PerplexingWiresModule": null,
    "superpositionRB": null,
    "ColorMorseModule": null,
    "DividedSquaresModule": null,
    "ro": null,
    "cruelCandyLand": null,
    "grayArrowsModule": null,
    "TheTwinModule": null,
    "MandMs": null,
    "TombstoneMazeModule": null,
    "AlienModule": null,
    "rustGB": null,
    "OutOfTime": null,
    "NandNs": null,
    "Mazery": null,
    "dragonEnergy": null,
    "forgetThis": null,
    "kookyKeypadModule": null,
    "spwizPerspectivePegs": null,
    "blackArrowsModule": null,
    "bamboozlingTimeKeeper": null,
    "forgetThemAll": null,
    "qkForgetPerspective": null,
    "Fillominordle": null,
    "RuleOfThreeModule": null,
    "colourCatch": null,
    "basegate": null,
    "ThreeCrypticSteps": null,
    "blueCipher": null,
    "LionsShareModule": null,
    "yellowCipher": null,
    "redCipher": null,
    "violetCipher": null,
    "coralCipher": null,
    "cornflowerCipher": null,
    "qkRepoSelector": null,
    "blackCipher": null,
    "forestCipher": null,
    "greenCipher": null,
    "rgbCombination": null,
    "blinkstopModule": null,
    "simonStashes": null,
    "SimonShinesModule": null,
    "brownCipher": null,
    "grayCipher": null,
    "whiteCipher": null,
    "ultimateCipher": null,
    "colorPong": null,
    "VarietyModule": null,
    "mazeSwap": null,
    "kataCheatCheckout": null,
    "creamCipher": null,
    "indigoCipher": null,
    "orangeCipher": null,
    "colouredCylinder": null,
    "IsocoloredSquaresModule": null,
    "synapseCipher": null,
    "magentaCipher": null,
    "coloredCube": null,
    "maroonCipher": null,
    "TheWeakestLink": null,
    "BicoloredSquaresModule": null,
    "OvercoloredSquaresModule": null,
    "1x1x1RubiksCube": null,
    "crimsonCipher": null,
    "rgbChess": null,
    "ShyGuySays": null,
    "epicShapes": null,
    "pointerPointerModule": null,
    "knotWires": null,
    "intensityLevels": null,
    "digitalClock": null,
    "airStrikes": null,
    "OrientationHypercube": null,
    "BlackoutModule": null,
    "TechnicalKeypad": null,
    "clockworks": null,
    "rgbLogic": null,
    "toeTactics": null
  }
}